weav_provider_router/__init__.py
weav_provider_router/api.py
weav_provider_router/base.py
weav_provider_router/providers.py
weav_provider_router/adapters/__init__.py
weav_provider_router/adapters/anthropic.py
weav_provider_router/adapters/baidu.py
weav_provider_router/adapters/bytedance.py
weav_provider_router/adapters/cohere.py
weav_provider_router/adapters/deepseek.py
weav_provider_router/adapters/google.py
weav_provider_router/adapters/groq.py
weav_provider_router/adapters/minimax.py
weav_provider_router/adapters/mistral.py
weav_provider_router/adapters/moonshot.py
weav_provider_router/adapters/nvidia.py
weav_provider_router/adapters/ollama.py
weav_provider_router/adapters/openai.py
weav_provider_router/adapters/openai_embedding.py
weav_provider_router/adapters/openai_image.py
weav_provider_router/adapters/qwen.py
weav_provider_router/adapters/together.py
weav_provider_router/adapters/zhipu.py
weav_provider_router-0.2.0.dist-info/licenses/LICENSE
weav_provider_router-0.2.0.dist-info/METADATA
weav_provider_router-0.2.0.dist-info/WHEEL
weav_provider_router-0.2.0.dist-info/top_level.txt
weav_provider_router-0.2.0.dist-info/RECORD
