Metadata-Version: 2.4
Name: weav-provider-router
Version: 0.2.0
Summary: A multi-modal AI provider router supporting LLM, image generation, and embeddings
Author: Weav Team
License: MIT
Project-URL: Homepage, https://github.com/HungryZhao/weav-provider-router
Project-URL: Documentation, https://github.com/HungryZhao/weav-provider-router/blob/main/README.md
Project-URL: Repository, https://github.com/HungryZhao/weav-provider-router
Project-URL: Issues, https://github.com/HungryZhao/weav-provider-router/issues
Keywords: llm,openai,anthropic,google,ollama,ai,nlp,image-generation,embeddings,dall-e,multi-modal,minimax,bytedance,nvidia
Classifier: Development Status :: 4 - Beta
Classifier: Intended Audience :: Developers
Classifier: License :: OSI Approved :: MIT License
Classifier: Programming Language :: Python :: 3
Classifier: Programming Language :: Python :: 3.9
Classifier: Programming Language :: Python :: 3.10
Classifier: Programming Language :: Python :: 3.11
Classifier: Programming Language :: Python :: 3.12
Classifier: Topic :: Software Development :: Libraries :: Python Modules
Classifier: Topic :: Scientific/Engineering :: Artificial Intelligence
Requires-Python: >=3.9
License-File: LICENSE
Provides-Extra: openai
Requires-Dist: openai>=1.0.0; extra == "openai"
Provides-Extra: anthropic
Requires-Dist: anthropic>=0.25.0; extra == "anthropic"
Provides-Extra: google
Requires-Dist: google-generativeai>=0.3.0; extra == "google"
Provides-Extra: ollama
Requires-Dist: ollama>=0.1.0; extra == "ollama"
Provides-Extra: all
Requires-Dist: openai>=1.0.0; extra == "all"
Requires-Dist: anthropic>=0.25.0; extra == "all"
Requires-Dist: google-generativeai>=0.3.0; extra == "all"
Requires-Dist: ollama>=0.1.0; extra == "all"
Provides-Extra: dev
Requires-Dist: pytest>=7.4.0; extra == "dev"
Requires-Dist: pytest-asyncio>=0.21.0; extra == "dev"
Requires-Dist: pytest-cov>=4.1.0; extra == "dev"
Requires-Dist: pytest-mock>=3.11.0; extra == "dev"
Requires-Dist: black>=23.7.0; extra == "dev"
Requires-Dist: ruff>=0.0.282; extra == "dev"
Requires-Dist: mypy>=1.4.1; extra == "dev"
Dynamic: license-file
